dogtail/__init__.py
dogtail/config.py
dogtail/distro.py
dogtail/dump.py
dogtail/errors.py
dogtail/i18n.py
dogtail/logging.py
dogtail/path.py
dogtail/predicate.py
dogtail/procedural.py
dogtail/rawinput.py
dogtail/sessions.py
dogtail/tc.py
dogtail/tree.py
dogtail/utils.py
dogtail/version.py
dogtail/wrapped.py
dogtail-1.0.7.data/data/share/applications/sniff.desktop
dogtail-1.0.7.data/data/share/doc/dogtail/examples/events-listener-script.py
dogtail-1.0.7.data/data/share/doc/dogtail/examples/gedit-stress-test-tree-api.py
dogtail-1.0.7.data/data/share/doc/dogtail/examples/gedit-test-utf8-tree-api.py
dogtail-1.0.7.data/data/share/doc/dogtail/examples/kwrite.py
dogtail-1.0.7.data/data/share/doc/dogtail/examples/data/10b.png
dogtail-1.0.7.data/data/share/doc/dogtail/examples/data/10w.png
dogtail-1.0.7.data/data/share/doc/dogtail/examples/data/20b.png
dogtail-1.0.7.data/data/share/doc/dogtail/examples/data/20w.png
dogtail-1.0.7.data/data/share/doc/dogtail/examples/data/UTF-8-demo.txt
dogtail-1.0.7.data/data/share/doc/dogtail/examples/data/sample.cfg
dogtail-1.0.7.data/data/share/doc/dogtail/tests/gtkdemotest.py
dogtail-1.0.7.data/data/share/doc/dogtail/tests/test_config.py
dogtail-1.0.7.data/data/share/doc/dogtail/tests/test_logging.py
dogtail-1.0.7.data/data/share/doc/dogtail/tests/test_predicate.py
dogtail-1.0.7.data/data/share/doc/dogtail/tests/test_procedural.py
dogtail-1.0.7.data/data/share/doc/dogtail/tests/test_rawinput.py
dogtail-1.0.7.data/data/share/doc/dogtail/tests/test_tree.py
dogtail-1.0.7.data/data/share/doc/dogtail/tests/test_utils.py
dogtail-1.0.7.data/data/share/doc/dogtail/tests/test_version.py
dogtail-1.0.7.data/data/share/dogtail/glade/sniff.ui
dogtail-1.0.7.data/data/share/dogtail/icons/button.png
dogtail-1.0.7.data/data/share/dogtail/icons/checkbutton.png
dogtail-1.0.7.data/data/share/dogtail/icons/checkmenuitem.png
dogtail-1.0.7.data/data/share/dogtail/icons/colorselection.png
dogtail-1.0.7.data/data/share/dogtail/icons/combo.png
dogtail-1.0.7.dist-info/licenses/COPYING
dogtail-1.0.7.dist-info/METADATA
dogtail-1.0.7.dist-info/WHEEL
dogtail-1.0.7.dist-info/top_level.txt
dogtail-1.0.7.dist-info/RECORD
