Metadata-Version: 2.4
Name: dogtail
Version: 1.0.7
Summary: GUI test tool and automation framework that uses Accessibility (a11y) technologies to communicate with desktop applications.
Home-page: https://gitlab.com/dogtail/dogtail
Author: Zack Cerza <zcerza@redhat.com>,
Author-email: Zack Cerza <zcerza@redhat.com>, Ed Rousseau <rousseau@redhat.com>, David Malcolm <dmalcolm@redhat.com>, Vitezslav Humpa <vhumpa@redhat.com>, Michal Odehnal <modehnal@redhat.com>
Project-URL: Homepage, https://gitlab.com/dogtail/dogtail
Requires-Python: >=3.6
License-File: COPYING
Dynamic: author
Dynamic: home-page
Dynamic: license-file
